sage_bootstrap
sage_root
