Metadata-Version: 2.4
Name: passagemath-bootstrap
Version: 10.6.31rc3
Summary: passagemath: Package database
Author-email: Volker Braun <vbraun.name@gmail.com>, The Sage Developers <sage-support@googlegroups.com>
Maintainer: Matthias Köppe, passagemath contributors
License-Expression: GPL-3.0-or-later
Project-URL: release notes, https://github.com/passagemath/passagemath/releases
Project-URL: repo (upstream), https://github.com/sagemath/sage
Project-URL: repo, https://github.com/passagemath/passagemath
Project-URL: documentation, https://passagemath.org/docs/latest
Project-URL: homepage (upstream), https://www.sagemath.org
Project-URL: discourse, https://passagemath.discourse.group
Project-URL: tracker (upstream), https://github.com/sagemath/sage/issues
Project-URL: tracker, https://github.com/passagemath/passagemath/issues
Classifier: Development Status :: 6 - Mature
Classifier: Intended Audience :: Education
Classifier: Intended Audience :: Science/Research
Classifier: Operating System :: POSIX
Classifier: Operating System :: MacOS :: MacOS X
Classifier: Programming Language :: Python :: 3 :: Only
Classifier: Programming Language :: Python :: 3.10
Classifier: Programming Language :: Python :: 3.11
Classifier: Programming Language :: Python :: 3.12
Classifier: Programming Language :: Python :: 3.13
Classifier: Programming Language :: Python :: Implementation :: CPython
Classifier: Topic :: Scientific/Engineering :: Mathematics
Requires-Python: !=3.0.*,!=3.1.*,!=3.2.*,!=3.3.*,<3.15,>=2.7
